lineshopping_api_mcp/__init__.py
lineshopping_api_mcp/app.py
lineshopping_api_mcp/openapi.json
lineshopping_api_mcp-0.1.0.dist-info/METADATA
lineshopping_api_mcp-0.1.0.dist-info/WHEEL
lineshopping_api_mcp-0.1.0.dist-info/entry_points.txt
lineshopping_api_mcp-0.1.0.dist-info/RECORD
