Metadata-Version: 2.4
Name: lineshopping-api-mcp
Version: 0.1.0
Summary: MCP Server for the LINE Shopping API, enabling AI agents to interact with LINE Shopping data and operations
Author-email: Woraphol <woraphol.j@gmail.com>
License: MIT
Keywords: ai-agent,api,line-shopping,mcp,model-context-protocol
Classifier: Development Status :: 3 - Alpha
Classifier: Intended Audience :: Developers
Classifier: License :: OSI Approved :: MIT License
Classifier: Programming Language :: Python :: 3
Classifier: Programming Language :: Python :: 3.11
Classifier: Programming Language :: Python :: 3.12
Classifier: Programming Language :: Python :: 3.13
Classifier: Topic :: Internet :: WWW/HTTP :: Dynamic Content
Classifier: Topic :: Software Development :: Libraries :: Python Modules
Requires-Python: >=3.11
Requires-Dist: fastmcp>=2.12.0
Requires-Dist: httpx>=0.25.0
